ros_map_editor/__init__.py
ros_map_editor/main.py
ros_map_editor/map_editor.py
ros_map_editor/ui_map_editor.py
ros_map_editor/version.py
ros_map_editor-0.1.2.dist-info/METADATA
ros_map_editor-0.1.2.dist-info/WHEEL
ros_map_editor-0.1.2.dist-info/entry_points.txt
ros_map_editor-0.1.2.dist-info/top_level.txt
ros_map_editor-0.1.2.dist-info/RECORD
