Metadata-Version: 2.4
Name: ros_map_editor
Version: 0.1.2
Summary: A GUI editor for ROS map files in PGM format
Home-page: https://github.com/sujit-168/ros_map_editor/tree/main
Author: sujit-168
Author-email: sujie@tianbot.com
Keywords: ros,map,editor,pgm,robotics
Classifier: Development Status :: 4 - Beta
Classifier: Intended Audience :: Developers
Classifier: Intended Audience :: Science/Research
Classifier: License :: OSI Approved :: MIT License
Classifier: Programming Language :: Python :: 3
Classifier: Programming Language :: Python :: 3.6
Classifier: Programming Language :: Python :: 3.7
Classifier: Programming Language :: Python :: 3.8
Classifier: Programming Language :: Python :: 3.9
Classifier: Topic :: Scientific/Engineering :: Visualization
Classifier: Topic :: Software Development :: User Interfaces
Requires-Python: >=3.6
Requires-Dist: PyQt5>=5.15.0
Requires-Dist: Pillow>=8.0.0
Requires-Dist: PyYAML>=5.1.0
Dynamic: author
Dynamic: author-email
Dynamic: classifier
Dynamic: description
Dynamic: description-content-type
Dynamic: home-page
Dynamic: keywords
Dynamic: requires-dist
Dynamic: requires-python
Dynamic: summary
